license
tmx2epub/__init__.py
tmx2epub/__main__.py
tmx2epub/browse_filename.py
tmx2epub/gen_epub.py
tmx2epub/xml_iter.py
tmx2epub-0.1.0.dist-info/entry_points.txt
tmx2epub-0.1.0.dist-info/license
tmx2epub-0.1.0.dist-info/WHEEL
tmx2epub-0.1.0.dist-info/METADATA
tmx2epub-0.1.0.dist-info/RECORD
