Metadata-Version: 2.1
Name: tmx2epub
Version: 0.1.0
Summary: converts tmx to epub
Home-page: https://github.com/ffreemt/tmx2epub
License: MIT
Keywords: tmx,epub,language,learning
Author: ffreemt
Requires-Python: >=3.7,<4.0
Classifier: Environment :: Console
Classifier: License :: OSI Approved :: MIT License
Classifier: Operating System :: OS Independent
Classifier: Programming Language :: Python :: 3
Classifier: Programming Language :: Python :: 3.7
Classifier: Programming Language :: Python :: 3.8
Classifier: Topic :: Software Development :: Libraries :: Python Modules
Requires-Dist: EbookLib (>=0.17.1,<0.18.0)
Requires-Dist: absl-py (>=0.9.0,<0.10.0)
Requires-Dist: logzero (>=1.5.0,<2.0.0)
Requires-Dist: more_itertools (>=8.4.0,<9.0.0)
Requires-Dist: pyquery (>=1.4.1,<2.0.0)
Requires-Dist: tqdm (>=4.47.0,<5.0.0)
Project-URL: Repository, https://github.com/ffreemt/tmx2epub
